{
	"info": {
		"_postman_id": "e305e94b-4a5f-4a0d-85fa-7fcf184285e6",
		"name": "EERS Enterprise API Collection",
		"description": "Postman Collection for EERS (Employee Expense Reimbursement System). Provides workflows for Employee submission, HOD review, Finance audit, and Accounts payables settlement.",
		"schema": "https://schema.getpostman.com/json/collection/v2.1.0/collection.json"
	},
	"item": [
		{
			"name": "1. Authentication",
			"item": [
				{
					"name": "Register Employee",
					"request": {
						"method": "POST",
						"header": [
							{
								"key": "Content-Type",
								"value": "application/json"
							}
						],
						"body": {
							"mode": "raw",
							"raw": "{\n  \"name\": \"Arjun Sharma\",\n  \"email\": \"arjun.sharma@company.com\",\n  \"password\": \"password123\",\n  \"role\": \"Employee\",\n  \"allottedBudget\": 15000\n}"
						},
						"url": {
							"raw": "{{base_url}}/api/auth/register",
							"host": [
								"{{base_url}}"
							],
							"path": [
								"api",
								"auth",
								"register"
							]
						}
					},
					"response": []
				},
				{
					"name": "Login User (Sarah - Employee)",
					"event": [
						{
							"listen": "test",
							"script": {
								"exec": [
									"const response = pm.response.json();",
									"if (response.token) {",
									"    pm.environment.set(\"jwt_token\", response.token);",
									"}"
								],
								"type": "text/javascript"
							}
						}
					],
					"request": {
						"method": "POST",
						"header": [
							{
								"key": "Content-Type",
								"value": "application/json"
							}
						],
						"body": {
							"mode": "raw",
							"raw": "{\n  \"email\": \"arjun.sharma@company.com\",\n  \"password\": \"password123\"\n}"
						},
						"url": {
							"raw": "{{base_url}}/api/auth/login",
							"host": [
								"{{base_url}}"
							],
							"path": [
								"api",
								"auth",
								"login"
							]
						}
					},
					"response": []
				},
				{
					"name": "Login User (Marcus - HOD)",
					"event": [
						{
							"listen": "test",
							"script": {
								"exec": [
									"const response = pm.response.json();",
									"if (response.token) {",
									"    pm.environment.set(\"jwt_token\", response.token);",
									"}"
								],
								"type": "text/javascript"
							}
						}
					],
					"request": {
						"method": "POST",
						"header": [
							{
								"key": "Content-Type",
								"value": "application/json"
							}
						],
						"body": {
							"mode": "raw",
							"raw": "{\n  \"email\": \"rajesh.deshmukh@company.com\",\n  \"password\": \"password123\"\n}"
						},
						"url": {
							"raw": "{{base_url}}/api/auth/login",
							"host": [
								"{{base_url}}"
							],
							"path": [
								"api",
								"auth",
								"login"
							]
						}
					},
					"response": []
				},
				{
					"name": "Login User (Linda - Finance)",
					"event": [
						{
							"listen": "test",
							"script": {
								"exec": [
									"const response = pm.response.json();",
									"if (response.token) {",
									"    pm.environment.set(\"jwt_token\", response.token);",
									"}"
								],
								"type": "text/javascript"
							}
						}
					],
					"request": {
						"method": "POST",
						"header": [
							{
								"key": "Content-Type",
								"value": "application/json"
							}
						],
						"body": {
							"mode": "raw",
							"raw": "{\n  \"email\": \"vivek.kulkarni@company.com\",\n  \"password\": \"password123\"\n}"
						},
						"url": {
							"raw": "{{base_url}}/api/auth/login",
							"host": [
								"{{base_url}}"
							],
							"path": [
								"api",
								"auth",
								"login"
							]
						}
					},
					"response": []
				},
				{
					"name": "Login User (Gary - Accounts)",
					"event": [
						{
							"listen": "test",
							"script": {
								"exec": [
									"const response = pm.response.json();",
									"if (response.token) {",
									"    pm.environment.set(\"jwt_token\", response.token);",
									"}"
								],
								"type": "text/javascript"
							}
						}
					],
					"request": {
						"method": "POST",
						"header": [
							{
								"key": "Content-Type",
								"value": "application/json"
							}
						],
						"body": {
							"mode": "raw",
							"raw": "{\n  \"email\": \"suresh.iyer@company.com\",\n  \"password\": \"password123\"\n}"
						},
						"url": {
							"raw": "{{base_url}}/api/auth/login",
							"host": [
								"{{base_url}}"
							],
							"path": [
								"api",
								"auth",
								"login"
							]
						}
					},
					"response": []
				},
				{
					"name": "Get Profile Info",
					"request": {
						"auth": {
							"type": "bearer",
							"bearer": [
								{
									"key": "token",
									"value": "{{jwt_token}}",
									"type": "string"
								}
							]
						},
						"method": "GET",
						"header": [],
						"url": {
							"raw": "{{base_url}}/api/auth/profile",
							"host": [
								"{{base_url}}"
							],
							"path": [
								"api",
								"auth",
								"profile"
							]
						}
					},
					"response": []
				}
			]
		},
		{
			"name": "2. Claims Management",
			"item": [
				{
					"name": "Submit New Claim (Sarah - Employee)",
					"request": {
						"auth": {
							"type": "bearer",
							"bearer": [
								{
									"key": "token",
									"value": "{{jwt_token}}",
									"type": "string"
								}
							]
						},
						"method": "POST",
						"header": [],
						"body": {
							"mode": "formdata",
							"formdata": [
								{
									"key": "title",
									"value": "Figma design tools license",
									"type": "text"
								},
								{
									"key": "categoryId",
									"value": "replace-with-seeding-category-id",
									"description": "Required (fetch via admin/categories first)",
									"type": "text"
								},
								{
									"key": "merchant",
									"value": "Figma Inc",
									"type": "text"
								},
								{
									"key": "amount",
									"value": "150.00",
									"type": "text"
								},
								{
									"key": "date",
									"value": "2026-06-28",
									"type": "text"
								},
								{
									"key": "description",
									"value": "Monthly subscription seat for designers.",
									"type": "text"
								},
								{
									"key": "isDraft",
									"value": "false",
									"type": "text"
								}
							]
						},
						"url": {
							"raw": "{{base_url}}/api/claims",
							"host": [
								"{{base_url}}"
							],
							"path": [
								"api",
								"claims"
							]
						}
					},
					"response": []
				},
				{
					"name": "Get Claims with query filters",
					"request": {
						"auth": {
							"type": "bearer",
							"bearer": [
								{
									"key": "token",
									"value": "{{jwt_token}}",
									"type": "string"
								}
							]
						},
						"method": "GET",
						"header": [],
						"url": {
							"raw": "{{base_url}}/api/claims?status=Submitted",
							"host": [
								"{{base_url}}"
							],
							"path": [
								"api",
								"claims"
							],
							"query": [
								{
									"key": "status",
									"value": "Submitted"
								}
							]
						}
					},
					"response": []
				},
				{
					"name": "Get Claim Detail by ID",
					"request": {
						"auth": {
							"type": "bearer",
							"bearer": [
								{
									"key": "token",
									"value": "{{jwt_token}}",
									"type": "string"
								}
							]
						},
						"method": "GET",
						"header": [],
						"url": {
							"raw": "{{base_url}}/api/claims/replace-with-claim-id",
							"host": [
								"{{base_url}}"
							],
							"path": [
								"api",
								"claims",
								"replace-with-claim-id"
							]
						}
					},
					"response": []
				}
			]
		},
		{
			"name": "3. Workflow Controls",
			"item": [
				{
					"name": "HOD / Finance decision (Approve/Reject)",
					"request": {
						"auth": {
							"type": "bearer",
							"bearer": [
								{
									"key": "token",
									"value": "{{jwt_token}}",
									"type": "string"
								}
							]
						},
						"method": "POST",
						"header": [
							{
								"key": "Content-Type",
								"value": "application/json"
							}
						],
						"body": {
							"mode": "raw",
							"raw": "{\n  \"action\": \"Approve\",\n  \"remarks\": \"Looks fully compliant and within budget constraints.\"\n}"
						},
						"url": {
							"raw": "{{base_url}}/api/approvals/replace-with-claim-id",
							"host": [
								"{{base_url}}"
							],
							"path": [
								"api",
								"approvals",
								"replace-with-claim-id"
							]
						}
					},
					"response": []
				},
				{
					"name": "Accounts Disburse Payment",
					"request": {
						"auth": {
							"type": "bearer",
							"bearer": [
								{
									"key": "token",
									"value": "{{jwt_token}}",
									"type": "string"
								}
							]
						},
						"method": "POST",
						"header": [
							{
								"key": "Content-Type",
								"value": "application/json"
							}
						],
						"body": {
							"mode": "raw",
							"raw": "{\n  \"transactionId\": \"TXN-BANK-1002345\",\n  \"method\": \"Bank Transfer\"\n}"
						},
						"url": {
							"raw": "{{base_url}}/api/payments/replace-with-claim-id",
							"host": [
								"{{base_url}}"
							],
							"path": [
								"api",
								"payments",
								"replace-with-claim-id"
							]
						}
					},
					"response": []
				}
			]
		},
		{
			"name": "4. Reports & Analytics",
			"item": [
				{
					"name": "Get Dashboard KPIs",
					"request": {
						"auth": {
							"type": "bearer",
							"bearer": [
								{
									"key": "token",
									"value": "{{jwt_token}}",
									"type": "string"
								}
							]
						},
						"method": "GET",
						"header": [],
						"url": {
							"raw": "{{base_url}}/api/reports/dashboard",
							"host": [
								"{{base_url}}"
							],
							"path": [
								"api",
								"reports",
								"dashboard"
							]
						}
					},
					"response": []
				},
				{
					"name": "Get Monthly Spend Chart data",
					"request": {
						"auth": {
							"type": "bearer",
							"bearer": [
								{
									"key": "token",
									"value": "{{jwt_token}}",
									"type": "string"
								}
							]
						},
						"method": "GET",
						"header": [],
						"url": {
							"raw": "{{base_url}}/api/reports/monthly",
							"host": [
								"{{base_url}}"
							],
							"path": [
								"api",
								"reports",
								"monthly"
							]
						}
					},
					"response": []
				},
				{
					"name": "Get Category aggregates for pie chart",
					"request": {
						"auth": {
							"type": "bearer",
							"bearer": [
								{
									"key": "token",
									"value": "{{jwt_token}}",
									"type": "string"
								}
							]
						},
						"method": "GET",
						"header": [],
						"url": {
							"raw": "{{base_url}}/api/reports/category",
							"host": [
								"{{base_url}}"
							],
							"path": [
								"api",
								"reports",
								"category"
							]
						}
					},
					"response": []
				}
			]
		}
	],
	"variable": [
		{
			"key": "base_url",
			"value": "http://localhost:5000",
			"type": "string"
		},
		{
			"key": "jwt_token",
			"value": "",
			"type": "string"
		}
	]
}
